chainhashing/__init__.py
chainhashing/claddress.py
chainhashing-1.0.3.dist-info/METADATA
chainhashing-1.0.3.dist-info/WHEEL
chainhashing-1.0.3.dist-info/licenses/LICENSE
chainhashing-1.0.3.dist-info/RECORD
