Metadata-Version: 2.3
Name: chainhashing
Version: 1.0.3
Summary: A package for closed addressing hash tables that require chaining with linked lists.
Project-URL: Homepage, https://github.com/Ruxton07/chainhashing
Project-URL: Issues, https://github.com/Ruxton07/chainhashing/issues
Author-email: Ruxton <rt.kellar@gmail.com>
License-File: LICENSE
Classifier: License :: OSI Approved :: MIT License
Classifier: Operating System :: OS Independent
Classifier: Programming Language :: Python :: 3
Requires-Python: >=3.8
